Workbook

Sheet Nike Data
A1: ($ in millions) | B1: FY 2025 | C1: FY 2024 | D1: FY 2023
A2: Revenues | B2: 46309 | C2: 51362 | D2: 51217
A3: Cost of Revenue | B3: 26519 | C3: 28475 | D3: 28925
A4: Gross Profit | B4: 19790 | C4: 22887 | D4: 22292
A5: Operating Income | B5: 3885 | C5: 6700 | D5: 5915
A6: Net Income | B6: 3219 | C6: 5700 | D6: 5070
A7: Interest Expense | B7: 107 | C7: 161 | D7: 6
A8: Total Current Assets | B8: 23362 | C8: 25382 | D8: 25202
A9: Total Assets | B9: 36579 | C9: 37531 | D9: 37531
A10: Total Current Liabilities | B10: 10566 | C10: 10593 | D10: 9256
A11: Total Liabilities | B11: 23366 | C11: 23860 | D11: 23527
A12: Total Shareholders' Equity | B12: 13213 | C12: 14430 | D12: 14004

Sheet Lulu Data
A1: ($ in thousands) | B1: FY 2025 | C1: FY 2024 | D1: FY 2023
A2: Revenues | B2: 11102600 | C2: 10588126 | D2: 9619278
A3: Gross Profit | B3: 6284132 | C3: 6270811 | D3: 5609405
A4: Operating Income | B4: 2210615 | C4: 2505697 | D4: 2207177
A5: Net Income | B5: 1579183 | C5: 1814616 | D5: 1550190
A6: Interest Expense | B6: 28352 | C6: 70380 | D6: -31442
A7: Total Current Assets | B7: 4262700 | C7: 3980302 | D7: 4060577
A8: Total Assets | B8: 8456743 | C8: 7603292 | D8: 7091941
A9: Total Current Liabilities | B9: 1888000 | C9: 1840000 | D9: 1631000
A10: Total Liabilities | B10: 3494903 | C10: 3279245 | D10: 2859860
A11: Total Shareholders' Equity | B11: 4961840 | C11: 4324047 | D11: 4232081

Sheet Ratio Dashbaord
A1: Category | B1: Ratio | C1: Nike FY2025 | D1: Nike FY2024 | E1: Nike FY2023 | F1: Lululemon FY2025 | G1: Lululemon FY2024 | H1: Lululemon FY2023
A2: Liquidity | B2: Current Ratio | C2: ='Nike Data'!B8/'Nike Data'!B10 -> 2.2110543 | D2: ='Nike Data'!C8/'Nike Data'!C10 -> 2.3961106 | E2: ='Nike Data'!D8/'Nike Data'!D10 -> 2.7227744 | F2: ='Lulu Data'!B7/'Lulu Data'!B9 -> 2.257786 | G2: ='Lulu Data'!C7/'Lulu Data'!C9 -> 2.1632076 | H2: ='Lulu Data'!D7/'Lulu Data'!D9 -> 2.4896242
A3: Profitability | B3: Gross Profit Margin | C3: ='Nike Data'!B4/'Nike Data'!B2 -> 0.42734674 | D3: ='Nike Data'!C4/'Nike Data'!C2 -> 0.44560181 | E3: ='Nike Data'!D4/'Nike Data'!D2 -> 0.43524611 | F3: ='Lulu Data'!B3/'Lulu Data'!B2 -> 0.56600544 | G3: ='Lulu Data'!C3/'Lulu Data'!C2 -> 0.59224937 | H3: ='Lulu Data'!D3/'Lulu Data'!D2 -> 0.583142
A4: Profitability | B4: Return on Equity (ROE) | C4: ='Nike Data'!B6/'Nike Data'!B12 -> 0.2436237 | D4: ='Nike Data'!C6/'Nike Data'!C12 -> 0.3950104 | E4: ='Nike Data'!D6/'Nike Data'!D12 -> 0.36203942 | F4: ='Lulu Data'!B5/'Lulu Data'!B11 -> 0.3182656 | G4: ='Lulu Data'!C5/'Lulu Data'!C11 -> 0.41965686 | H4: ='Lulu Data'!D5/'Lulu Data'!D11 -> 0.36629497
A5: Solvency | B5: Debt-to-Equity | C5: ='Nike Data'!B11/'Nike Data'!B12 -> 1.7684099 | D5: ='Nike Data'!C11/'Nike Data'!C12 -> 1.6534997 | E5: ='Nike Data'!D11/'Nike Data'!D12 -> 1.68002 | F5: ='Lulu Data'!B10/'Lulu Data'!B11 -> 0.70435625 | G5: ='Lulu Data'!C10/'Lulu Data'!C11 -> 0.75837404 | H5: ='Lulu Data'!D10/'Lulu Data'!D11 -> 0.67575739
A6: Efficiency | B6: Asset Turnover | C6: ='Nike Data'!B2/AVERAGE('Nike Data'!B9:D9) -> 1.2444084 | D6: ='Nike Data'!C2/AVERAGE('Nike Data'!B9:D9) -> 1.3801919 | E6: ='Nike Data'!D2/AVERAGE('Nike Data'!C9:E9) -> 1.3646585 | F6: ='Lulu Data'!B2/AVERAGE('Lulu Data'!B8:D8) -> 1.4386591 | G6: ='Lulu Data'!C2/AVERAGE('Lulu Data'!B8:D8) -> 1.3719943 | H6: ='Lulu Data'!D2/AVERAGE('Lulu Data'!C8:E8) -> 1.3091699

Sheet Charts
